bunnynet/__init__.py
bunnynet/client.py
bunnynet/exceptions.py
bunnynet/hashing.py
bunnynet/httpclient.py
bunnynet/log_client.py
bunnynet/models/__init__.py
bunnynet/models/bunny_ai_image_blueprint.py
bunnynet/models/edge_rule.py
bunnynet/models/edge_rule_action_type.py
bunnynet/models/edge_rule_trigger.py
bunnynet/models/edge_rule_trigger_type.py
bunnynet/models/hostname.py
bunnynet/models/pattern_matching_type.py
bunnynet/models/pull_zone.py
bunnynet/models/pull_zone_type.py
bunnynet/models/storage_object.py
bunnynet/models/storage_zone.py
bunnynet/models/trigger_matching_type.py
bunnynet/pull_zone_client.py
bunnynet/storage_endpoints.py
bunnynet/storage_zone_client.py
bunnynet-0.3.0.dist-info/LICENSE
bunnynet-0.3.0.dist-info/METADATA
bunnynet-0.3.0.dist-info/WHEEL
bunnynet-0.3.0.dist-info/RECORD
