Metadata-Version: 2.1
Name: bunnynet
Version: 0.3.0
Summary: A client for the bunny.net APIs
Home-page: https://github.com/dalemyers/bunnynet
License: MIT
Keywords: bunny,bunny.net,cdn
Author: Dale Myers
Author-email: dale@myers.io
Requires-Python: >=3.10,<4.0
Classifier: Development Status :: 3 - Alpha
Classifier: Environment :: Console
Classifier: Intended Audience :: Developers
Classifier: License :: OSI Approved :: MIT License
Classifier: Programming Language :: Python :: 3
Classifier: Programming Language :: Python :: 3.10
Classifier: Programming Language :: Python :: 3.11
Classifier: Programming Language :: Python :: 3
Classifier: Programming Language :: Python :: 3.10
Classifier: Programming Language :: Python :: 3.11
Classifier: Topic :: Software Development
Classifier: Topic :: Utilities
Requires-Dist: deserialize (>=2.0.1,<3.0.0)
Requires-Dist: requests (>=2.28.2,<3.0.0)
Requires-Dist: tenacity (>=8.2.2,<9.0.0)
Project-URL: Repository, https://github.com/dalemyers/bunnynet
